mailgun/__init__.py
mailgun/email_parsing.py
mailgun/error.py
mailgun/mailgun.py
mailgun3_python-0.1.4.dist-info/LICENSE
mailgun3_python-0.1.4.dist-info/METADATA
mailgun3_python-0.1.4.dist-info/WHEEL
mailgun3_python-0.1.4.dist-info/top_level.txt
mailgun3_python-0.1.4.dist-info/RECORD
