Metadata-Version: 2.1
Name: mailgun3-python
Version: 0.1.4
Summary: Mailgun client for python
Home-page: https://github.com/docsumo/mailgun3_python
Author: Docsumo
Author-email: hello@docsumo.com
License: MIT
Platform: UNKNOWN
Classifier: Intended Audience :: Education
Classifier: Intended Audience :: Science/Research
Classifier: Intended Audience :: Developers
Classifier: License :: OSI Approved :: MIT License
Classifier: Programming Language :: Python
Classifier: Programming Language :: Python :: 3
Classifier: Topic :: Scientific/Engineering
Classifier: Topic :: Software Development
Requires-Python: >=3
Requires-Dist: requests
